Workbook

Sheet Flujo de Caja
B1: FLUJO DE CAJA
B2: 0 | C2: 1 | D2: 2 | E2: 3 | F2: 4 | G2: 5 | H2: (Meses)
A3: Ingresos
A4: Hitos de pago | C4: =Ingresos!B12 -> 28244880 | E4: =Ingresos!C12 -> 21183660 | G4: =Ingresos!D12 -> 21183660
A5: TOTAL INGRESOS | C5: =SUM(C4) -> 28244880 | D5: =SUM(D4) -> 0 | E5: =SUM(E4) -> 21183660 | F5: =SUM(F4) -> 0 | G5: =SUM(G4) -> 21183660
A6: Costos
A7: Sueldos | C7: =Costos!$K$9 -> 8480000 | D7: =Costos!$K$9 -> 8480000 | E7: =Costos!$K$9 -> 8480000 | F7: =Costos!$K$9 -> 8480000 | G7: =Costos!$K$9 -> 8480000
A8: Tecnologías | C8: =Costos!$F$16+Costos!$F$17 -> 0 | D8: =Costos!$F$16+Costos!$F$17 -> 0 | E8: =Costos!$F$16+Costos!$F$17 -> 0 | F8: =Costos!$F$16+Costos!$F$17 -> 0 | G8: =Costos!$F$16+Costos!$F$17 -> 0
A9: TOTAL COSTOS | C9: =SUM(C7:C8) -> 8480000 | D9: =SUM(D7:D8) -> 8480000 | E9: =SUM(E7:E8) -> 8480000 | F9: =SUM(F7:F8) -> 8480000 | G9: =SUM(G7:G8) -> 8480000
A10: Gastos Administrativos
A11: Viaticos | C11: 70000 | D11: 70000 | E11: 70000 | F11: 70000 | G11: 70000
A12: Cowork | C12: 50400 | D12: 50400 | E12: 50400 | F12: 50400 | G12: 50400
A13: TOTAL GASTOS | C13: =SUM(C11,C12) -> 120400 | D13: =SUM(D11,D12) -> 120400 | E13: =SUM(E11,E12) -> 120400 | F13: =SUM(F11,F12) -> 120400 | G13: =SUM(G11,G12) -> 120400
A14: Otros gastos
A15: Retribución capital | C15: ='Aporte de Capital'!$G$5+'Aporte de Capital'!$E$5 -> 2625000
A16: Depreciación | C16: ='Depreciación'!$F$13 -> 129997.5 | D16: ='Depreciación'!$F$13 -> 129997.5 | E16: ='Depreciación'!$F$13 -> 129997.5 | F16: ='Depreciación'!$F$13 -> 129997.5 | G16: ='Depreciación'!$F$13 -> 129997.5
A17: Beneficio Tributario | G17: =SUM(C16:G16) -> 649987.5
A18: Utilidad antes de impuesto | C18: =C5-C9-C13 -> 19644480 | D18: =D5-D9-D13 -> -8600400 | E18: =E5-E9-E13 -> 12583260 | F18: =F5-F9-F13 -> -8600400 | G18: =G5-G9-G13 -> 12583260
A19: Utilidad antes de impuesto final | G19: =SUM(C18:G18)-G17 -> 26960212
A20: Impuesto (27%) | G20: =G19*0.27 -> 7279257.4
A21: Utilidad después de impuesto | C21: =C18-($G$20/5) -> 18188629 | D21: =D18-($G$20/5) -> -10056251 | E21: =E18-($G$20/5) -> 11127409 | F21: =F18-($G$20/5) -> -10056251 | G21: =G18-($G$20/5) -> 11127409
A22: (+) Depreciación | C22: =C16 -> 129997.5 | D22: =D16 -> 129997.5 | E22: =E16 -> 129997.5 | F22: =F16 -> 129997.5 | G22: =G16 -> 129997.5
A23: (-) Inversión Inicial | B23: =-'Inversión'!$E$6 -> -2079960
A24: (-)(+) Capital de trabajo | B24: =-'Capital de Trabajo'!$B$18 -> -3982860
A25: (+)(-) Aporte de capital | B25: ='Aporte de Capital'!$D$17 -> 2100000 | G25: =-(B25+(SUM(C15:G15))) -> -4725000
A26: FLUJO DE CAJA | B26: =SUM(B23:B25) -> -3962820 | C26: =C21+C22 -> 18318626 | D26: =D21+D22 -> -9926254 | E26: =E21+E22 -> 11257406 | F26: =F21+F22 -> -9926254 | G26: =G21+G22+G25 -> 6532406
A28: K | B28: 0.27
A30: VAN | B30: {=NPV(B28,C26:G26)+B26} -> 7964308.5
A31: TIR | B31: =IRR(B26:G26) -> 3.1549254
A32: ROI | B32: =('Capital de Trabajo'!H14-'Capital de Trabajo'!H15)/'Capital de Trabajo'!H15 -> 0.56630723
A33: Relación Beneficio Costo | B33: ='Capital de Trabajo'!H14/'Capital de Trabajo'!H15 -> 1.5663072
A34: Payback | B34: =PayBack!$E$3 -> 1

Sheet PayBack
B2: PAYBACK | E2: Periodo Recuperación
B3: PERIODO | C3: FLUJO CAJA | D3: RECUPERACIÓN | E3: 1
B4: 0 | C4: ='Flujo de Caja'!$B$26 -> -3962820 | D4: ='Flujo de Caja'!$B$26 -> -3962820
B5: 1 | C5: ='Flujo de Caja'!$C$26 -> 18318626 | D5: =D4+C5 -> 14355806 | E5: Valor positivo, se recupera la inversión
B6: 2 | C6: ='Flujo de Caja'!$D$26 -> -9926254 | D6: =D5+C6 -> 4429552
B7: 3 | C7: ='Flujo de Caja'!$E$26 -> 11257406 | D7: =D6+C7 -> 15686958
B8: 4 | C8: ='Flujo de Caja'!$F$26 -> -9926254 | D8: =D7+C8 -> 5760704.1
B9: 5 | C9: ='Flujo de Caja'!$G$26 -> 6532406 | D9: =D8+C9 -> 12293110

Sheet Backlog
A1: Etapas | B1: Tareas | C1: Pesimista | D1: Optimista | E1: Valor en horas | F1: Total | H1: Total Horas | I1: Total Dias | J1: Total Meses
A2: Análisis | B2: AN - 1 Recopilacion de historia de usuario | C2: 15 | D2: 6 | E2: =AVERAGE(C2:D2) -> 10.5 | F2: =sum(E2:E6) -> 80 | H2: =sum(F2:F31) -> 797 | I2: =H2/8 -> 99.625 | J2: =I2/20 -> 4.98125
B3: AN - 2 Extracion Requisitos funcionales | C3: 8 | D3: 4 | E3: =AVERAGE(C3:D3) -> 6
B4: AN - 3 Extracion Requisitos No funcionales | C4: 8 | D4: 4 | E4: =AVERAGE(C4:D4) -> 6
B5: AN - 4 Puntuacion de Tareas | C5: 50 | D5: 25 | E5: =AVERAGE(C5:D5) -> 37.5
B6: AN - 5 Revision y Aprobación | C6: 24 | D6: 16 | E6: =AVERAGE(C6:D6) -> 20
A7: Diseño | B7: DÑO-1 Establecer metas para el diseño | C7: 8 | D7: 5 | E7: =AVERAGE(C7,D7) -> 6.5 | F7: =SUM(E7:E12) -> 130
B8: DÑO-2 Definir criterio de exito del diseño | C8: 8 | D8: 5 | E8: =AVERAGE(C8,D8) -> 6.5
B9: DÑO-3 Creacion de Prototipo | C9: 24 | D9: 16 | E9: =AVERAGE(C9,D9) -> 20
B10: DÑO-4 Validacion del aspecto visual | C10: 10 | D10: 8 | E10: =AVERAGE(C10,D10) -> 9
B11: DÑO-5 Validacion de usabilidad del diseño | C11: 16 | D11: 10 | E11: =AVERAGE(C11,D11) -> 13
B12: DÑO-6 Validacion con cliente | C12: 100 | D12: 50 | E12: =AVERAGE(C12,D12) -> 75
A13: Desarrollo | B13: DE - 1 Desarrollo de servicios frontend | C13: 180 | D13: 140 | E13: =AVERAGE(C13,D13) -> 160 | F13: =SUM(E13,E14,E15) -> 395
B14: DE - 2 Desarrollo de backend | C14: 220 | D14: 180 | E14: =AVERAGE(C14,D14) -> 200
B15: DE - 3 Desarrollo de la red neuronal | C15: 40 | D15: 30 | E15: =AVERAGE(C15,D15) -> 35
A16: Testing | B16: TEST - 1 Planificación de Pruebas | C16: 8 | D16: 16 | E16: =AVERAGE(C16,D16) -> 12 | F16: =SUM(E16,E17,E18,E19,E20,E21,E22) -> 69
B17: TEST -2 2 Diseño de Casos de Prueba | C17: 16 | D17: 20 | E17: =AVERAGE(C17,D17) -> 18
B18: TEST - 3 Configuración del Entorno de Pruebas | C18: 8 | D18: 4 | E18: =AVERAGE(C18,D18) -> 6
B19: TEST - 4. Ejecución de Pruebas | C19: 4 | D19: 2 | E19: =AVERAGE(C19,D19) -> 3
B20: TEST - 5 Registro de Defectos y Seguimiento | C20: 8 | D20: 16 | E20: =AVERAGE(C20,D20) -> 12
B21: TEST - 6 Informes y Documentación | C21: 8 | D21: 16 | E21: =AVERAGE(C21,D21) -> 12
B22: TEST - 7 Revisión y Aprobación | C22: 4 | D22: 8 | E22: =AVERAGE(C22,D22) -> 6
A23: Implementación | B23: IMP 1 - Preparación para la Implementación | C23: 8 | D23: 4 | E23: =AVERAGE(C23,D23) -> 6 | F23: =sum(E23:E26) -> 84.5
B24: IMP 2 - Despliegue de la Solución | C24: 25 | D24: 14 | E24: =AVERAGE(C24,D24) -> 19.5
B25: IMP 3 - Transición y Puesta en Marcha | C25: 60 | D25: 36 | E25: =AVERAGE(C25,D25) -> 48
B26: IMP 4- Evaluación Post-Implementación | C26: 15 | D26: 7 | E26: =AVERAGE(C26,D26) -> 11
A27: Capacitación | B27: CAP-1 Preparación de material | C27: 12 | D27: 8 | E27: =AVERAGE(C27,D27) -> 10 | F27: =SUM(E27:E31) -> 38.5
B28: CAP-2 Creacion de manual | C28: 10 | D28: 5 | E28: =AVERAGE(C28,D28) -> 7.5
B29: CAP-3 Planificación de sesiones | C29: 11 | D29: 6 | E29: =AVERAGE(C29,D29) -> 8.5
B30: CAP- 4 Impartir capacitacion | C30: 12 | D30: 8 | E30: =AVERAGE(C30,D30) -> 10
B31: CAP-5 Cierre y entrega del manual | C31: 3 | D31: 2 | E31: =AVERAGE(C31,D31) -> 2.5

Sheet Inversión
A2: Cantidad | B2: Ítem | C2: Inversión Inicial | D2: observación | E2: TOTAL | G2: Referencias | I2: Iva
A3: 4 | B3: Notebook | C3: 519990 | D3: Valor neto | E3: =A3*C3 -> 2079960 | G3: https://ztech.cl/products/notebook-lenovo-thinkpad-l14-gen-4-core-i5-13va-16-gb-ram-512gb-ssd-21h20011cl-mod-usado | I3: 0.19
C6: Inversión inicial | D6: TOTAL | E6: =SUM(E3:E4) -> 2079960

Sheet Aporte de Capital
C3: General
C4: Cantidad socios | D4: Aporte individual | E4: Total Aporte | F4: % Tasa Retribución | G4: Ganancia esperada | H4: Ganacia individual
C5: 7 | D5: 300000 | E5: =C5*D5 -> 2100000 | F5: 0.25 | G5: =E5*F5 -> 525000 | H5: =G5/C5 -> 75000
C8: Detalle
C9: Nombre socio | D9: Aporte
C10: Natalia Quintana | D10: 300000
C11: Juan Perez | D11: 300000
C12: Brayan Román | D12: 300000
C13: Claudio Toro | D13: 300000
C14: Juan Cordova | D14: 300000
C15: Raul Gonzalez | D15: 300000
C16: Osvaldo Valdenegro | D16: 300000
C17: Total | D17: =SUM(D10:D16) -> 2100000
C19: Supuesto | D19: Se espera que el aporte total devuelto sea de $2.625.000

Sheet Ingresos
C1: HITOS
B2: Ingresos | C2: 1800 | D2: UF | G2: UF | H2: 39229
B4: CLP | C4: =C2*H2 -> 70612200
B5: Valor horas | C5: 2.56 | D5: UF
B7: Son 5 períodos
B9: HITOS DE PAGO
B10: 1 | C10: 2 | D10: 3
B11: 0.4 | C11: 0.3 | D11: 0.3 | E11: TOTAL
B12: =C4*B11 -> 28244880 | C12: =C4*C11 -> 21183660 | D12: =D11*C4 -> 21183660 | E12: =SUM(B12:D12) -> 70612200
B18: Etapas | C18: Fechas | D18: Observación
B19: Primera etapa | D19: La primera entrega contempla nuestras etapas de análisis,diseño y la primera etapa del desarrollo.
B22: Segunda etapa | D22: La segunda entrega contempla la segunda etapa de desarrollo y testing.
B25: Tercera etapa | D25: La tercera entrega contempla la implementacion y además la capacitación

Sheet Costos
D2: Sueldo + descuentos legales
C3: Cargo | D3: Liquido | E3: Salud | F3: AFP | G3: Seguro Censantía | H3: Bono Teletrabajo | I3: Bono Colación
B4: Sueldos | E4: 0.07 | F4: 0.12 | G4: 0.03 | J4: Unitario | K4: TOTAL
B5: 1 | C5: Jefe de Proyecto | D5: 2000000 | E5: =D5*E4 -> 140000 | F5: =F4*D5 -> 240000 | G5: =D5*G4 -> 60000 | H5: 35000 | I5: 75000 | J5: =SUM(D5:I5) -> 2550000 | K5: =J5*B5 -> 2550000
B6: 2 | C6: Programador full stack | D6: 1400000 | E6: =D6*E4 -> 98000 | F6: =F4*D6 -> 168000 | G6: =G4*D6 -> 42000 | H6: 35000 | I6: 75000 | J6: =SUM(D6:I6) -> 1818000 | K6: =J6*B6 -> 3636000
B7: 1 | C7: QA | D7: 700000 | E7: =D7*E4 -> 49000 | F7: =F4*D7 -> 84000 | G7: =D7*G4 -> 21000 | H7: 35000 | I7: 75000 | J7: =SUM(D7:I7) -> 964000 | K7: =J7*B7 -> 964000
B8: 1 | C8: Consultor | D8: 1000000 | E8: =D8*E4 -> 70000 | F8: =F4*D8 -> 120000 | G8: =D8*G4 -> 30000 | H8: 35000 | I8: 75000 | J8: =SUM(D8:I8) -> 1330000 | K8: =J8*B8 -> 1330000
J9: Total | K9: =SUM(K5:K8) -> 8480000

Sheet Capital de Trabajo
B1: 0 | C1: 1 | D1: 2 | E1: 3 | F1: 4 | G1: 5
A2: Ingresos
A3: Hitos de pago | C3: =Ingresos!B12 -> 28244880 | E3: =Ingresos!C12 -> 21183660 | G3: =Ingresos!D12 -> 21183660
A4: TOTAL INGRESOS | C4: =SUM(C3) -> 28244880 | D4: =SUM(D3) -> 0 | E4: =SUM(E3) -> 21183660 | F4: =SUM(F3) -> 0 | G4: =SUM(G3) -> 21183660
A5: Costos
A6: Sueldos | C6: =Costos!$K$9 -> 8480000 | D6: =Costos!$K$9 -> 8480000 | E6: =Costos!$K$9 -> 8480000 | F6: =Costos!$K$9 -> 8480000 | G6: =Costos!$K$9 -> 8480000
A7: TOTAL COSTOS | C7: =SUM(C6) -> 8480000 | D7: =SUM(D6) -> 8480000 | E7: =SUM(E6) -> 8480000 | F7: =SUM(F6) -> 8480000 | G7: =SUM(G6) -> 8480000
A8: Gastos Administrativos
A9: Viaticos | C9: 70000 | D9: 70000 | E9: 70000 | F9: 70000 | G9: 70000
A10: Cowork | C10: 50400 | D10: 50400 | E10: 50400 | F10: 50400 | G10: 50400
A11: TOTAL GASTOS | C11: =SUM(C9,C10) -> 120400 | D11: =SUM(D9,D10) -> 120400 | E11: =SUM(E9,E10) -> 120400 | F11: =SUM(F9,F10) -> 120400 | G11: =SUM(G9,G10) -> 120400
A12: Inversión inicial | B12: ='Inversión'!E6 -> 2079960
H13: TOTAL
A14: Ingresos | C14: =C4 -> 28244880 | D14: =D4 -> 0 | E14: =E4 -> 21183660 | F14: =F4 -> 0 | G14: =G4 -> 21183660 | H14: =SUM(C14:G14) -> 70612200
A15: Egresos | B15: =SUM(B12:B14) -> 2079960 | C15: =C7+C11 -> 8600400 | D15: =D7+D11 -> 8600400 | E15: =E7+E11 -> 8600400 | F15: =F7+F11 -> 8600400 | G15: =G7+G11 -> 8600400 | H15: =SUM(B15:G15) -> 45081960
A16: Total Líquido | B16: =B14-B15 -> -2079960 | C16: =C14-C15 -> 19644480 | D16: =D14-D15 -> -8600400 | E16: =E14-E15 -> 12583260 | F16: =F14-F15 -> -8600400 | G16: =G14-G15 -> 12583260
A17: Acumulado | B17: =B16+C16 -> 17564520 | C17: =C16+D16 -> 11044080 | D17: =D16+E16 -> 3982860 | E17: =E16+F16 -> 3982860 | F17: =F16+G16 -> 3982860 | G17: =G16 -> 12583260
A18: Mínimo | B18: =MIN(B17:G17) -> 3982860

Sheet Depreciación
A5: Nro | B5: Activo Fijo | C5: Valor Compra | D5: Vida Útil | E5: Depreciación Anual | F5: Cuota Mensual | I5: Referencia
A6: 1 | B6: Notebook | C6: 519990 | D6: 2 | E6: =C6/D6 -> 259995 | F6: =E6/12 -> 21666.25 | I6: NUEVA TABLA DE VIDA UTIL DE LOS BIENES FISICOS DEL ACTIVO INMOVILIZADO
A7: 2 | B7: Notebook | C7: 519990 | D7: 2 | E7: =C7/D7 -> 259995 | F7: =E7/12 -> 21666.25 | I7: https://ztech.cl/products/notebook-lenovo-thinkpad-l14-gen-4-core-i5-13va-16-gb-ram-512gb-ssd-21h20011cl-mod-usado
A8: 3 | B8: Notebook | C8: 519990 | D8: 2 | E8: =C8/D8 -> 259995 | F8: =E8/12 -> 21666.25
A9: 4 | B9: Notebook | C9: 519990 | D9: 2 | E9: =C9/D9 -> 259995 | F9: =E9/12 -> 21666.25
A10: 5 | B10: Notebook | C10: 519990 | D10: 2 | E10: =C10/D10 -> 259995 | F10: =E10/12 -> 21666.25
A11: 6 | B11: Notebook | C11: 519990 | D11: 2 | E11: =C11/D11 -> 259995 | F11: =E11/12 -> 21666.25
E13: TOTAL | F13: =SUM(F6:F12) -> 129997.5
C15: Vida Útil | D15: 2 | E15: Años
